cfanalysis/__init__.py
cfanalysis/cfafunctions.py
cfanalysis-0.1.9.dist-info/METADATA
cfanalysis-0.1.9.dist-info/WHEEL
cfanalysis-0.1.9.dist-info/top_level.txt
cfanalysis-0.1.9.dist-info/RECORD
