Metadata-Version: 2.1
Name: cfanalysis
Version: 0.1.9
Summary: Library to perform Combinatorial Fusion Analysis
Author: Mohammed Quazi
Requires-Dist: numpy
Requires-Dist: pandas
Requires-Dist: PyTDC
